predator/__init__.py
predator/__main__.py
predator/graph.py
predator/predator.py
predator/sbml.py
predator/utils.py
predator/asp/enum-cc.lp
predator/asp/greedy-target-seed-solving-seed-minimality-constraint.lp
predator/asp/greedy-target-seed-solving.lp
predator/asp/iterative-target-seed-solving--aim.lp
predator/asp/pareto-seed-solving.lp
predator/asp/pareto_utnu_avoid_targets_as_seeds.lp
predator/asp/pareto_utnu_scope_seeds.lp
predator/asp/simple-seed-solving.lp
predator-0.0.4.dist-info/LICENCE.txt
predator-0.0.4.dist-info/METADATA
predator-0.0.4.dist-info/WHEEL
predator-0.0.4.dist-info/top_level.txt
predator-0.0.4.dist-info/RECORD
