Metadata-Version: 2.1
Name: predator
Version: 0.0.4
Summary: Optimizable seed extraction from metabolic networks
Home-page: https://github.com/aluriak/predator
Author: Lucas Bourneuf
Author-email: lucas.bourneuf@inria.fr
License: GPL
Keywords: Answer Set Programming,wrapper,clingo
Platform: UNKNOWN
Classifier: Development Status :: 4 - Beta
Classifier: Intended Audience :: Science/Research
Classifier: Programming Language :: Python :: 3
Classifier: Programming Language :: Python :: 3.5
Classifier: Programming Language :: Python :: 3.6
Classifier: Programming Language :: Python :: 3.7
Classifier: Programming Language :: ASP
Requires-Dist: clyngor (>=0.3.18)
Requires-Dist: networkx (==2.2)
Requires-Dist: pytest (>=4.4.0)
